LICENSE
README.md
setup.py
aiowmi/__init__.py
aiowmi/buf.py
aiowmi/cim_type.py
aiowmi/connection.py
aiowmi/const.py
aiowmi/dcom.py
aiowmi/dcom_const.py
aiowmi/exceptions.py
aiowmi/protocol.py
aiowmi/qcontext.py
aiowmi/query.py
aiowmi/request.py
aiowmi/tools.py
aiowmi/uuid.py
aiowmi/version.py
aiowmi.egg-info/PKG-INFO
aiowmi.egg-info/SOURCES.txt
aiowmi.egg-info/dependency_links.txt
aiowmi.egg-info/requires.txt
aiowmi.egg-info/top_level.txt
aiowmi/dtypes/__init__.py
aiowmi/dtypes/dt.py
aiowmi/dtypes/lpwstr.py
aiowmi/dtypes/wordstr.py
aiowmi/ndr/__init__.py
aiowmi/ndr/activation_blob.py
aiowmi/ndr/activation_context_info_data.py
aiowmi/ndr/class_part.py
aiowmi/ndr/com_version.py
aiowmi/ndr/common.py
aiowmi/ndr/const.py
aiowmi/ndr/dualstring_array.py
aiowmi/ndr/encoded_string.py
aiowmi/ndr/encoded_value.py
aiowmi/ndr/encoding_unit.py
aiowmi/ndr/get_smart_enum_response.py
aiowmi/ndr/heap.py
aiowmi/ndr/instantiation_info_data.py
aiowmi/ndr/interface.py
aiowmi/ndr/location_info_data.py
aiowmi/ndr/ndr_info_data.py
aiowmi/ndr/next_big_response.py
aiowmi/ndr/next_response.py
aiowmi/ndr/ntlm_login_response.py
aiowmi/ndr/object_block.py
aiowmi/ndr/objref.py
aiowmi/ndr/objref_custom.py
aiowmi/ndr/objref_standard.py
aiowmi/ndr/objref_std.py
aiowmi/ndr/orpcthat.py
aiowmi/ndr/orpcthis.py
aiowmi/ndr/properties.py
aiowmi/ndr/property_info.py
aiowmi/ndr/props_out_info.py
aiowmi/ndr/qualifier.py
aiowmi/ndr/qualifier_set.py
aiowmi/ndr/query_response.py
aiowmi/ndr/rem_query_interface_response.py
aiowmi/ndr/remote_create_instance.py
aiowmi/ndr/remote_create_instance_response.py
aiowmi/ndr/scm_reply_info_data.py
aiowmi/ndr/scm_request_info_data.py
aiowmi/ndr/smart_response.py
aiowmi/ndr/varying_array.py
aiowmi/ndr/wbem_datapacket_object.py
aiowmi/ndr/wbem_object.py
aiowmi/ntlm/__init__.py
aiowmi/ntlm/auth_authenticate.py
aiowmi/ntlm/auth_challange.py
aiowmi/ntlm/auth_negotiate.py
aiowmi/ntlm/av_pairs.py
aiowmi/ntlm/const.py
aiowmi/ntlm/login.py
aiowmi/ntlm/message_signature.py
aiowmi/ntlm/tools.py
aiowmi/ntlm/version.py
aiowmi/rpc/__init__.py
aiowmi/rpc/auth_verifier_co.py
aiowmi/rpc/baseresp.py
aiowmi/rpc/bind.py
