Metadata-Version: 2.1
Name: aiowmi
Version: 0.2.3
Summary: Python WMI Queries
Home-page: https://github.com/cesbit/aiowmi
Download-URL: https://github.com/cesbit/aiowmi/tarball/v0.2.3
Author: Jeroen van der Heijden
Author-email: jeroen@cesbit.com
License: UNKNOWN
Keywords: WMI,Monitoring
Platform: UNKNOWN
Classifier: Intended Audience :: Developers
Classifier: Operating System :: OS Independent
Classifier: Programming Language :: Python :: 3.7
Classifier: Programming Language :: Python :: 3.8
Classifier: Programming Language :: Python :: 3.9
Classifier: Programming Language :: Python :: 3.10
Classifier: Programming Language :: Python :: 3 :: Only
Classifier: Topic :: Software Development :: Libraries :: Python Modules
Classifier: Topic :: Text Processing :: Linguistic
License-File: LICENSE
